minsound/__init__.py
minsound/base.py
minsound/bell.py
minsound/proc.py
minsound/wrap.py
minsound-0.1.0.dist-info/LICENSE
minsound-0.1.0.dist-info/METADATA
minsound-0.1.0.dist-info/WHEEL
minsound-0.1.0.dist-info/top_level.txt
minsound-0.1.0.dist-info/RECORD
