Metadata-Version: 2.1
Name: minsound
Version: 0.1.0
Summary: 🔊 Play music and sounds in your Python scripts
Home-page: UNKNOWN
Author: Alex DeLorenzo
License: LGPL-3.0
Platform: UNKNOWN
Requires-Python: >=3.6
License-File: LICENSE
Requires-Dist: anyio
Requires-Dist: boombox
Requires-Dist: playsound
Requires-Dist: sniffio
